nest/__init__.py
nest/clean_up.py
nest/config.json
nest/config.py
nest/exceptions.py
nest/global_variables.py
nest/logging_helper.py
nest/network_utilities.py
nest/topology_map.py
nest/user.py
nest/version.py
nest/engine/__init__.py
nest/engine/dynamic_routing.py
nest/engine/exec.py
nest/engine/ip_address.py
nest/engine/ip_link.py
nest/engine/ip_mpls_route.py
nest/engine/ip_netns.py
nest/engine/ip_route.py
nest/engine/iperf3.py
nest/engine/ipv6_states.py
nest/engine/iterators.py
nest/engine/netperf.py
nest/engine/ping.py
nest/engine/setns.py
nest/engine/sysctl.py
nest/engine/tc.py
nest/engine/uname.py
nest/engine/util.py
nest/experiment/__init__.py
nest/experiment/experiment.py
nest/experiment/pack.py
nest/experiment/results.py
nest/experiment/run_exp.py
nest/experiment/info/README.txt
nest/experiment/parser/__init__.py
nest/experiment/parser/iperf3.py
nest/experiment/parser/netperf.py
nest/experiment/parser/ping.py
nest/experiment/parser/runnerbase.py
nest/experiment/parser/ss.py
nest/experiment/parser/tc.py
nest/experiment/parser/iterators/ss.sh
nest/experiment/parser/iterators/tc.sh
nest/experiment/plotter/__init__.py
nest/experiment/plotter/common.py
nest/experiment/plotter/iperf3.py
nest/experiment/plotter/netperf.py
nest/experiment/plotter/ping.py
nest/experiment/plotter/ss.py
nest/experiment/plotter/tc.py
nest/routing/__init__.py
nest/routing/isis.py
nest/routing/ldp.py
nest/routing/ospf.py
nest/routing/rip.py
nest/routing/route_daemons.py
nest/routing/routing_helper.py
nest/routing/zebra.py
nest/tests/__init__.py
nest/tests/test_experiment.py
nest/tests/test_routing_frr.py
nest/tests/test_routing_frr_ipv6.py
nest/tests/test_routing_quagga.py
nest/tests/test_routing_quagga_ipv6.py
nest/tests/test_static_routing_mpls.py
nest/tests/test_topology.py
nest/tests/test_topology_address.py
nest/tests/test_topology_address_ipv6.py
nest/tests/test_topology_map.py
nest/topology/__init__.py
nest/topology/address.py
nest/topology/id_generator.py
nitk_nest-0.3.dist-info/AUTHORS.txt
nitk_nest-0.3.dist-info/LICENSE
nitk_nest-0.3.dist-info/METADATA
nitk_nest-0.3.dist-info/WHEEL
nitk_nest-0.3.dist-info/top_level.txt
nitk_nest-0.3.dist-info/RECORD
